lfsr.v
module lfsr (clk,set,out);
    input clk,set ;
    output reg [2:0] out ;
    always @(posedge clk) begin
        if(set)
            out<=3'b110 ;

        else
            out<={out[1],out[0],out[2]^out[0]};
    end
endmodule

lfsr_tb.v
`timescale 1ns/10ps
module lfsr_tb;
reg clk,set;
wire [2:0] out;
lfsr ans (clk ,set ,out);
initial begin
    clk=0;
    set=0;

end
always #50 clk=~clk;
initial #50 set=1'b1;
initial #150 set=1'b0;
initial #2000 $finish;
initial begin
    $dumpfile("lfsr.vcd");
    $dumpvars(0,ans);
end
endmodule

lfsr.vcd
$date
	Thu May 19 10:36:09 2022
$end
$version
	Icarus Verilog
$end
$timescale
	10ps
$end
$scope module lfsr_tb $end
$scope module ans $end
$var wire 1 ! clk $end
$var wire 1 " set $end
$var reg 3 # out [2:0] $end
$upscope $end
$upscope $end
$enddefinitions $end
#0
$dumpvars
bx #
0"
0!
$end
#5000
b110 #
1"
1!
#10000
0!
#15000
b101 #
1!
0"
#20000
0!
#25000
b10 #
1!
#30000
0!
#35000
b100 #
1!
#40000
0!
#45000
b1 #
1!
#50000
0!
#55000
b11 #
1!
#60000
0!
#65000
b111 #
1!
#70000
0!
#75000
b110 #
1!
#80000
0!
#85000
b101 #
1!
#90000
0!
#95000
b10 #
1!
#100000
0!
#105000
b100 #
1!
#110000
0!
#115000
b1 #
1!
#120000
0!
#125000
b11 #
1!
#130000
0!
#135000
b111 #
1!
#140000
0!
#145000
b110 #
1!
#150000
0!
#155000
b101 #
1!
#160000
0!
#165000
b10 #
1!
#170000
0!
#175000
b100 #
1!
#180000
0!
#185000
b1 #
1!
#190000
0!
#195000
b11 #
1!
